pytee.py
setup.py
pytee.egg-info/PKG-INFO
pytee.egg-info/SOURCES.txt
pytee.egg-info/dependency_links.txt
pytee.egg-info/top_level.txt