Metadata-Version: 1.0
Name: pytee
Version: 0.1
Summary: A implementation of tee in Python
Home-page: http://github.com/bsandrow/pytee
Author: Brandon Sandrowicz
Author-email: brandon@sandrowicz.org
License: UNKNOWN
Platform: UNKNOWN
